AUTHORS.md
CHANGELOG.md
CONTRIBUTING.md
LICENSE
MANIFEST.in
README.md
setup.py
openschemas/__init__.py
openschemas/version.py
openschemas.egg-info/PKG-INFO
openschemas.egg-info/SOURCES.txt
openschemas.egg-info/dependency_links.txt
openschemas.egg-info/entry_points.txt
openschemas.egg-info/not-zip-safe
openschemas.egg-info/requires.txt
openschemas.egg-info/top_level.txt
openschemas/cli/__init__.py
openschemas/cli/validate.py
openschemas/cli/map2model/__init__.py
openschemas/logger/__init__.py
openschemas/logger/message.py
openschemas/logger/progress.py
openschemas/logger/spinner.py
openschemas/main/__init__.py
openschemas/main/base/Dockerfile
openschemas/main/base/README.md
openschemas/main/base/__init__.py
openschemas/main/base/command.py
openschemas/main/base/flags.py
openschemas/main/base/generate.py
openschemas/main/base/logger.py
openschemas/main/map2model/README.md
openschemas/main/map2model/__init__.py
openschemas/main/map2model/file_manager.py
openschemas/main/map2model/mapping.py
openschemas/main/map2model/parser.py
openschemas/main/map2model/validator.py
openschemas/main/map2model/templates/__init__.py
openschemas/main/map2model/templates/template.html
openschemas/main/validate/__init__.py
openschemas/main/validate/helpers.py
openschemas/main/validate/criteria/__init__.py
openschemas/main/validate/criteria/base.py
openschemas/main/validate/criteria/dummy.yml
openschemas/main/validate/criteria/specification.yml
openschemas/main/validate/criteria/structure.py
openschemas/utils/__init__.py
openschemas/utils/fileio.py
openschemas/utils/managers.py
openschemas/utils/terminal.py
openschemas/utils/web.py