Metadata-Version: 1.1
Name: openschemas
Version: 0.0.14
Summary: openschemas python helper functions for schemaorg schemas
Home-page: https://www.github.com/openschemas/openschemas-python
Author: Vanessa Sochat
Author-email: vsochat@stanford.edu
License: LICENSE
Keywords: openschemas,markdown,schemaorg,rdf
Platform: UNKNOWN
Classifier: Intended Audience :: Science/Research
Classifier: Intended Audience :: Developers
Classifier: Programming Language :: Python
Classifier: Topic :: Software Development
Classifier: Topic :: Scientific/Engineering
Classifier: Operating System :: Unix
Classifier: Programming Language :: Python :: 2.7
Classifier: Programming Language :: Python :: 3
